espeakng_loader/__init__.py
espeakng_loader/espeak-ng-data/af_dict
espeakng_loader/espeak-ng-data/am_dict
espeakng_loader/espeak-ng-data/an_dict
espeakng_loader/espeak-ng-data/ar_dict
espeakng_loader/espeak-ng-data/as_dict
espeakng_loader/espeak-ng-data/az_dict
espeakng_loader/espeak-ng-data/ba_dict
espeakng_loader/espeak-ng-data/be_dict
espeakng_loader/espeak-ng-data/bg_dict
espeakng_loader/espeak-ng-data/bn_dict
espeakng_loader/espeak-ng-data/bpy_dict
espeakng_loader/espeak-ng-data/bs_dict
espeakng_loader/espeak-ng-data/ca_dict
espeakng_loader/espeak-ng-data/chr_dict
espeakng_loader/espeak-ng-data/cmn_dict
espeakng_loader/espeak-ng-data/cs_dict
espeakng_loader/espeak-ng-data/cv_dict
espeakng_loader/espeak-ng-data/cy_dict
espeakng_loader/espeak-ng-data/da_dict
espeakng_loader/espeak-ng-data/de_dict
espeakng_loader/espeak-ng-data/el_dict
espeakng_loader/espeak-ng-data/en_dict
espeakng_loader/espeak-ng-data/eo_dict
espeakng_loader/espeak-ng-data/es_dict
espeakng_loader/espeak-ng-data/et_dict
espeakng_loader/espeak-ng-data/eu_dict
espeakng_loader/espeak-ng-data/fa_dict
espeakng_loader/espeak-ng-data/fi_dict
espeakng_loader/espeak-ng-data/fr_dict
espeakng_loader/espeak-ng-data/ga_dict
espeakng_loader/espeak-ng-data/gd_dict
espeakng_loader/espeak-ng-data/gn_dict
espeakng_loader/espeak-ng-data/grc_dict
espeakng_loader/espeak-ng-data/gu_dict
espeakng_loader/espeak-ng-data/hak_dict
espeakng_loader/espeak-ng-data/haw_dict
espeakng_loader/espeak-ng-data/he_dict
espeakng_loader/espeak-ng-data/hi_dict
espeakng_loader/espeak-ng-data/hr_dict
espeakng_loader/espeak-ng-data/ht_dict
espeakng_loader/espeak-ng-data/hu_dict
espeakng_loader/espeak-ng-data/hy_dict
espeakng_loader/espeak-ng-data/ia_dict
espeakng_loader/espeak-ng-data/id_dict
espeakng_loader/espeak-ng-data/intonations
espeakng_loader/espeak-ng-data/io_dict
espeakng_loader/espeak-ng-data/is_dict
espeakng_loader/espeak-ng-data/it_dict
espeakng_loader/espeak-ng-data/ja_dict
espeakng_loader/espeak-ng-data/jbo_dict
espeakng_loader-0.2.3.dist-info/METADATA
espeakng_loader-0.2.3.dist-info/WHEEL
espeakng_loader-0.2.3.dist-info/RECORD
