Metadata-Version: 2.4
Name: espeakng-loader
Version: 0.2.3
Summary: A Python package that provides shared library loader for eSpeak NG
Author-email: thewh1teagle <61390950+thewh1teagle@users.noreply.github.com>
Requires-Python: >=3.6
